<?xml version="1.0" encoding="UTF-8"?>
<objects serializationModel="Studio.02.02.00">
	<object class="DAWProject" id="{395cd868-a80b-45da-9b69-8768d5676bcc}">
		<property name="assetPath">
			<value>Bubble Team 73 Music.rpp.link/</value>
		</property>
		<property name="dawProjectPath">
			<value>Bubble Team 73 Music/Bubble Team 73 Music.rpp</value>
		</property>
		<property name="renderedAssetsPath">
			<value>../Music Renders</value>
		</property>
		<relationship name="masterAssetFolder">
			<destination>{5960e3ec-e478-4d13-bc2c-f125b1d6cf87}</destination>
		</relationship>
	</object>
</objects>
